fix/__init__.py
fix/module.py
pystarpix-1.0.0.dist-info/METADATA
pystarpix-1.0.0.dist-info/WHEEL
pystarpix-1.0.0.dist-info/top_level.txt
pystarpix-1.0.0.dist-info/RECORD
