Metadata-Version: 2.1
Name: pystarpix
Version: 1.0.0
Summary: only star pix
Author: crandi
